ribbons/__init__.py
ribbons-0.0.0.dist-info/DESCRIPTION.rst
ribbons-0.0.0.dist-info/METADATA
ribbons-0.0.0.dist-info/RECORD
ribbons-0.0.0.dist-info/WHEEL
ribbons-0.0.0.dist-info/metadata.json
ribbons-0.0.0.dist-info/top_level.txt
